nb2workflow/__init__.py
nb2workflow/container.py
nb2workflow/cwl.py
nb2workflow/deploy.py
nb2workflow/galaxy.py
nb2workflow/health.py
nb2workflow/helpers.py
nb2workflow/json.py
nb2workflow/logging_setup.py
nb2workflow/logstash.py
nb2workflow/model.py
nb2workflow/nbadapter.py
nb2workflow/ontology.py
nb2workflow/publish.py
nb2workflow/schedule.py
nb2workflow/semantics.py
nb2workflow/sentry.py
nb2workflow/service.py
nb2workflow/testing.py
nb2workflow/validate.py
nb2workflow/workflows.py
nb2workflow/templates/Dockerfile.jinja
nb2workflow/templates/buildjob.yaml.jinja
nb2workflow/templates/deployment.yaml.jinja
nb2workflow/templates/dockerfile_cm.yaml.jinja
nb2workflow/templates/pvc.yaml.jinja
nb2workflow/templates/service.yaml.jinja
nb2workflow-1.3.115.dist-info/licenses/LICENSE
nb2workflow-1.3.115.dist-info/METADATA
nb2workflow-1.3.115.dist-info/WHEEL
nb2workflow-1.3.115.dist-info/entry_points.txt
nb2workflow-1.3.115.dist-info/top_level.txt
nb2workflow-1.3.115.dist-info/RECORD
