Metadata-Version: 2.4
Name: nb2workflow
Version: 1.3.115
Summary: convert notebook to workflow
Home-page: https://github.com/volodymyrss/nb2workflow
Download-URL: https://github.com/volodymyrss/nb2workflow/archive/1.0.1.tar.gz
Author: Volodymyr Savchenko
Author-email: contact@volodymyrsavchenko.com
License: GPLv3
Keywords: jupyter,docker
Requires-Python: >=3.9,<3.14
License-File: LICENSE
Requires-Dist: papermill
Requires-Dist: ipykernel
Requires-Dist: nbconvert
Requires-Dist: psutil
Requires-Dist: diskcache
Requires-Dist: requests
Requires-Dist: pyyaml
Requires-Dist: scrapbook
Requires-Dist: werkzeug==2.0.3
Requires-Dist: validators==0.28.3
Requires-Dist: sentry_sdk
Requires-Dist: rdflib
Requires-Dist: GitPython
Requires-Dist: typeguard; python_version > "3.9"
Requires-Dist: typeguard<4.4.3; python_version == "3.9"
Requires-Dist: oda_api
Provides-Extra: service
Requires-Dist: flask==2.0.3; extra == "service"
Requires-Dist: pytest-flask; extra == "service"
Requires-Dist: flask-caching; extra == "service"
Requires-Dist: flask-cors; extra == "service"
Requires-Dist: flasgger; extra == "service"
Requires-Dist: python-consul; extra == "service"
Requires-Dist: apscheduler; extra == "service"
Requires-Dist: beautifulsoup4; extra == "service"
Provides-Extra: rdf
Requires-Dist: rdflib; extra == "rdf"
Requires-Dist: owlready2==0.11; extra == "rdf"
Requires-Dist: oda-knowledge-base; extra == "rdf"
Provides-Extra: cwl
Requires-Dist: cwlgen; extra == "cwl"
Provides-Extra: docker
Requires-Dist: docker; extra == "docker"
Requires-Dist: checksumdir; extra == "docker"
Requires-Dist: Jinja2; extra == "docker"
Provides-Extra: domains
Requires-Dist: numpy; extra == "domains"
Requires-Dist: astropy; extra == "domains"
Requires-Dist: pandas; extra == "domains"
Requires-Dist: matplotlib; extra == "domains"
Provides-Extra: mmoda
Provides-Extra: k8s
Requires-Dist: kubernetes; extra == "k8s"
Requires-Dist: Jinja2; extra == "k8s"
Provides-Extra: galaxy
Requires-Dist: bibtexparser>=2.0.0b3; extra == "galaxy"
Requires-Dist: pypandoc_binary; extra == "galaxy"
Requires-Dist: black; extra == "galaxy"
Requires-Dist: isort; extra == "galaxy"
Requires-Dist: autoflake; extra == "galaxy"
Dynamic: author
Dynamic: author-email
Dynamic: download-url
Dynamic: home-page
Dynamic: keywords
Dynamic: license
Dynamic: license-file
Dynamic: provides-extra
Dynamic: requires-dist
Dynamic: requires-python
Dynamic: summary
